[
    {
        "Ticker": "AAPL",
        "Model": "DMA",
        "Strategy": "SMA",
        "Best_Window": 7,
        "Metric_Value": 9.983510787794298,
        "Metric_Type": "roi",
        "Signal": "Hold",
        "Nominal_Buy": 0,
        "Aggressive_Buy": 0.0,
        "Sentiment_Score": null
    },
    {
        "Ticker": "NVDA",
        "Model": "DMA",
        "Strategy": "SMA",
        "Best_Window": 100,
        "Metric_Value": 320.39117929238336,
        "Metric_Type": "roi",
        "Signal": "Hold",
        "Nominal_Buy": 0,
        "Aggressive_Buy": 0.0,
        "Sentiment_Score": null
    },
    {
        "Ticker": "MSFT",
        "Model": "DMA",
        "Strategy": "SMA",
        "Best_Window": 86,
        "Metric_Value": 6.999433616703444,
        "Metric_Type": "roi",
        "Signal": "Buy",
        "Nominal_Buy": 50,
        "Aggressive_Buy": 97.1557379921409,
        "Sentiment_Score": null
    },
    {
        "Ticker": "AMZN",
        "Model": "DMA",
        "Strategy": "SMA",
        "Best_Window": 10,
        "Metric_Value": 8.345884380413587,
        "Metric_Type": "roi",
        "Signal": "Buy",
        "Nominal_Buy": 50,
        "Aggressive_Buy": 68.5295905742775,
        "Sentiment_Score": null
    },
    {
        "Ticker": "META",
        "Model": "DMA",
        "Strategy": "SMA",
        "Best_Window": 47,
        "Metric_Value": 5.616946302076696,
        "Metric_Type": "roi",
        "Signal": "Buy",
        "Nominal_Buy": 50,
        "Aggressive_Buy": 98.64542549154093,
        "Sentiment_Score": null
    },
    {
        "Ticker": "GOOG",
        "Model": "DMA",
        "Strategy": "SMA",
        "Best_Window": 53,
        "Metric_Value": 10.17975600787762,
        "Metric_Type": "roi",
        "Signal": "Buy",
        "Nominal_Buy": 50,
        "Aggressive_Buy": 69.03840296904136,
        "Sentiment_Score": null
    },
    {
        "Ticker": "BRK-B",
        "Model": "DMA",
        "Strategy": "SMA",
        "Best_Window": 72,
        "Metric_Value": 2.1972477588706676,
        "Metric_Type": "roi",
        "Signal": "Hold",
        "Nominal_Buy": 0,
        "Aggressive_Buy": 0.0,
        "Sentiment_Score": null
    },
    {
        "Ticker": "TSLA",
        "Model": "DMA",
        "Strategy": "SMA",
        "Best_Window": 5,
        "Metric_Value": 49.63706259459217,
        "Metric_Type": "roi",
        "Signal": "Hold",
        "Nominal_Buy": 0,
        "Aggressive_Buy": 0.0,
        "Sentiment_Score": null
    },
    {
        "Ticker": "BLK",
        "Model": "DMA",
        "Strategy": "SMA",
        "Best_Window": 95,
        "Metric_Value": 3.2724122518658545,
        "Metric_Type": "roi",
        "Signal": "Hold",
        "Nominal_Buy": 0,
        "Aggressive_Buy": 0.0,
        "Sentiment_Score": null
    },
    {
        "Ticker": "PLTR",
        "Model": "DMA",
        "Strategy": "SMA",
        "Best_Window": 100,
        "Metric_Value": 8.104633973087632,
        "Metric_Type": "roi",
        "Signal": "Buy",
        "Nominal_Buy": 50,
        "Aggressive_Buy": 142.33117107566923,
        "Sentiment_Score": null
    },
    {
        "Ticker": "COIN",
        "Model": "DMA",
        "Strategy": "SMA",
        "Best_Window": 100,
        "Metric_Value": 0.924969468268549,
        "Metric_Type": "roi",
        "Signal": "Buy",
        "Nominal_Buy": 50,
        "Aggressive_Buy": 104.36333432503737,
        "Sentiment_Score": null
    },
    {
        "Ticker": "HOOD",
        "Model": "DMA",
        "Strategy": "SMA",
        "Best_Window": 100,
        "Metric_Value": 6.5748419486711995,
        "Metric_Type": "roi",
        "Signal": "Hold",
        "Nominal_Buy": 0,
        "Aggressive_Buy": 0.0,
        "Sentiment_Score": null
    },
    {
        "Ticker": "PATH",
        "Model": "DMA",
        "Strategy": "SMA",
        "Best_Window": 100,
        "Metric_Value": -0.33777724562405326,
        "Metric_Type": "roi",
        "Signal": "Buy",
        "Nominal_Buy": 50,
        "Aggressive_Buy": 96.48622916794164,
        "Sentiment_Score": null
    },
    {
        "Ticker": "SNOW",
        "Model": "DMA",
        "Strategy": "SMA",
        "Best_Window": 100,
        "Metric_Value": 0.4376418869733911,
        "Metric_Type": "roi",
        "Signal": "Hold",
        "Nominal_Buy": 0,
        "Aggressive_Buy": 0.0,
        "Sentiment_Score": null
    },
    {
        "Ticker": "APP",
        "Model": "DMA",
        "Strategy": "SMA",
        "Best_Window": 100,
        "Metric_Value": 17.660327434244515,
        "Metric_Type": "roi",
        "Signal": "Hold",
        "Nominal_Buy": 0,
        "Aggressive_Buy": 0.0,
        "Sentiment_Score": null
    },
    {
        "Ticker": "AVGO",
        "Model": "DMA",
        "Strategy": "SMA",
        "Best_Window": 23,
        "Metric_Value": 61.883612096438895,
        "Metric_Type": "roi",
        "Signal": "Buy",
        "Nominal_Buy": 50,
        "Aggressive_Buy": 75.63062500758795,
        "Sentiment_Score": null
    },
    {
        "Ticker": "LLY",
        "Model": "DMA",
        "Strategy": "SMA",
        "Best_Window": 19,
        "Metric_Value": 15.067341327812409,
        "Metric_Type": "roi",
        "Signal": "Buy",
        "Nominal_Buy": 50,
        "Aggressive_Buy": 55.024253112344226,
        "Sentiment_Score": null
    },
    {
        "Ticker": "JPM",
        "Model": "DMA",
        "Strategy": "SMA",
        "Best_Window": 100,
        "Metric_Value": 6.049022207611511,
        "Metric_Type": "roi",
        "Signal": "Hold",
        "Nominal_Buy": 0,
        "Aggressive_Buy": 0.0,
        "Sentiment_Score": null
    },
    {
        "Ticker": "UNH",
        "Model": "DMA",
        "Strategy": "SMA",
        "Best_Window": 10,
        "Metric_Value": 3.356680671247309,
        "Metric_Type": "roi",
        "Signal": "Hold",
        "Nominal_Buy": 0,
        "Aggressive_Buy": 0.0,
        "Sentiment_Score": null
    },
    {
        "Ticker": "V",
        "Model": "DMA",
        "Strategy": "SMA",
        "Best_Window": 89,
        "Metric_Value": 5.018201966577162,
        "Metric_Type": "roi",
        "Signal": "Hold",
        "Nominal_Buy": 0,
        "Aggressive_Buy": 0.0,
        "Sentiment_Score": null
    },
    {
        "Ticker": "XOM",
        "Model": "DMA",
        "Strategy": "SMA",
        "Best_Window": 100,
        "Metric_Value": 1.9114412771577884,
        "Metric_Type": "roi",
        "Signal": "Buy",
        "Nominal_Buy": 50,
        "Aggressive_Buy": 94.91707172743764,
        "Sentiment_Score": null
    },
    {
        "Ticker": "MA",
        "Model": "DMA",
        "Strategy": "SMA",
        "Best_Window": 12,
        "Metric_Value": 5.248347881052228,
        "Metric_Type": "roi",
        "Signal": "Buy",
        "Nominal_Buy": 50,
        "Aggressive_Buy": 55.945868203743764,
        "Sentiment_Score": null
    },
    {
        "Ticker": "ORCL",
        "Model": "DMA",
        "Strategy": "SMA",
        "Best_Window": 59,
        "Metric_Value": 3.1984906285809296,
        "Metric_Type": "roi",
        "Signal": "Buy",
        "Nominal_Buy": 50,
        "Aggressive_Buy": 69.88640944814412,
        "Sentiment_Score": null
    },
    {
        "Ticker": "COST",
        "Model": "DMA",
        "Strategy": "SMA",
        "Best_Window": 21,
        "Metric_Value": 6.115317975386732,
        "Metric_Type": "roi",
        "Signal": "Buy",
        "Nominal_Buy": 50,
        "Aggressive_Buy": 64.62033891559089,
        "Sentiment_Score": null
    },
    {
        "Ticker": "PG",
        "Model": "DMA",
        "Strategy": "SMA",
        "Best_Window": 7,
        "Metric_Value": 1.0699121379253476,
        "Metric_Type": "roi",
        "Signal": "Buy",
        "Nominal_Buy": 50,
        "Aggressive_Buy": 57.622686273223714,
        "Sentiment_Score": null
    },
    {
        "Ticker": "HD",
        "Model": "DMA",
        "Strategy": "SMA",
        "Best_Window": 5,
        "Metric_Value": 3.09341034409159,
        "Metric_Type": "roi",
        "Signal": "Buy",
        "Nominal_Buy": 50,
        "Aggressive_Buy": 56.79383788216115,
        "Sentiment_Score": null
    },
    {
        "Ticker": "JNJ",
        "Model": "DMA",
        "Strategy": "SMA",
        "Best_Window": 5,
        "Metric_Value": 1.797079746709659,
        "Metric_Type": "roi",
        "Signal": "Buy",
        "Nominal_Buy": 50,
        "Aggressive_Buy": 53.57560628272368,
        "Sentiment_Score": null
    },
    {
        "Ticker": "NFLX",
        "Model": "DMA",
        "Strategy": "SMA",
        "Best_Window": 100,
        "Metric_Value": 25.41755548838264,
        "Metric_Type": "roi",
        "Signal": "Buy",
        "Nominal_Buy": 50,
        "Aggressive_Buy": 160.51182058946296,
        "Sentiment_Score": null
    },
    {
        "Ticker": "ABBV",
        "Model": "DMA",
        "Strategy": "SMA",
        "Best_Window": 11,
        "Metric_Value": 2.9076059075070133,
        "Metric_Type": "roi",
        "Signal": "Hold",
        "Nominal_Buy": 0,
        "Aggressive_Buy": 0.0,
        "Sentiment_Score": null
    },
    {
        "Ticker": "BAC",
        "Model": "DMA",
        "Strategy": "SMA",
        "Best_Window": 100,
        "Metric_Value": 4.022143464242773,
        "Metric_Type": "roi",
        "Signal": "Hold",
        "Nominal_Buy": 0,
        "Aggressive_Buy": 0.0,
        "Sentiment_Score": null
    },
    {
        "Ticker": "CRM",
        "Model": "DMA",
        "Strategy": "SMA",
        "Best_Window": 6,
        "Metric_Value": 1.1275358870679395,
        "Metric_Type": "roi",
        "Signal": "Buy",
        "Nominal_Buy": 50,
        "Aggressive_Buy": 76.83966060136899,
        "Sentiment_Score": null
    },
    {
        "Ticker": "WMT",
        "Model": "DMA",
        "Strategy": "SMA",
        "Best_Window": 99,
        "Metric_Value": 4.285996243075426,
        "Metric_Type": "roi",
        "Signal": "Buy",
        "Nominal_Buy": 50,
        "Aggressive_Buy": 82.74370332161203,
        "Sentiment_Score": null
    },
    {
        "Ticker": "KO",
        "Model": "DMA",
        "Strategy": "SMA",
        "Best_Window": 75,
        "Metric_Value": 1.3803587265299235,
        "Metric_Type": "roi",
        "Signal": "Hold",
        "Nominal_Buy": 0,
        "Aggressive_Buy": 0.0,
        "Sentiment_Score": null
    },
    {
        "Ticker": "CVX",
        "Model": "DMA",
        "Strategy": "SMA",
        "Best_Window": 95,
        "Metric_Value": 1.42535410440942,
        "Metric_Type": "roi",
        "Signal": "Buy",
        "Nominal_Buy": 50,
        "Aggressive_Buy": 86.62248382558431,
        "Sentiment_Score": null
    },
    {
        "Ticker": "MRK",
        "Model": "DMA",
        "Strategy": "SMA",
        "Best_Window": 33,
        "Metric_Value": 1.7695428158483117,
        "Metric_Type": "roi",
        "Signal": "Hold",
        "Nominal_Buy": 0,
        "Aggressive_Buy": 0.0,
        "Sentiment_Score": null
    },
    {
        "Ticker": "ADBE",
        "Model": "DMA",
        "Strategy": "SMA",
        "Best_Window": 11,
        "Metric_Value": 1.2131828148706756,
        "Metric_Type": "roi",
        "Signal": "Buy",
        "Nominal_Buy": 50,
        "Aggressive_Buy": 107.51903170834693,
        "Sentiment_Score": null
    },
    {
        "Ticker": "WFC",
        "Model": "DMA",
        "Strategy": "SMA",
        "Best_Window": 100,
        "Metric_Value": 1.8727980874093266,
        "Metric_Type": "roi",
        "Signal": "Hold",
        "Nominal_Buy": 0,
        "Aggressive_Buy": 0.0,
        "Sentiment_Score": null
    },
    {
        "Ticker": "PEP",
        "Model": "DMA",
        "Strategy": "SMA",
        "Best_Window": 6,
        "Metric_Value": 0.8023213458221564,
        "Metric_Type": "roi",
        "Signal": "Buy",
        "Nominal_Buy": 50,
        "Aggressive_Buy": 59.890297795606905,
        "Sentiment_Score": null
    },
    {
        "Ticker": "TMO",
        "Model": "DMA",
        "Strategy": "SMA",
        "Best_Window": 64,
        "Metric_Value": 2.4648212986986144,
        "Metric_Type": "roi",
        "Signal": "Buy",
        "Nominal_Buy": 50,
        "Aggressive_Buy": 65.44624747117341,
        "Sentiment_Score": null
    },
    {
        "Ticker": "LIN",
        "Model": "DMA",
        "Strategy": "SMA",
        "Best_Window": 91,
        "Metric_Value": 3.0479791458351517,
        "Metric_Type": "roi",
        "Signal": "Hold",
        "Nominal_Buy": 0,
        "Aggressive_Buy": 0.0,
        "Sentiment_Score": null
    },
    {
        "Ticker": "AMD",
        "Model": "DMA",
        "Strategy": "SMA",
        "Best_Window": 100,
        "Metric_Value": 104.07000764743749,
        "Metric_Type": "roi",
        "Signal": "Hold",
        "Nominal_Buy": 0,
        "Aggressive_Buy": 0.0,
        "Sentiment_Score": null
    },
    {
        "Ticker": "DIS",
        "Model": "DMA",
        "Strategy": "SMA",
        "Best_Window": 5,
        "Metric_Value": 0.3993214153775332,
        "Metric_Type": "roi",
        "Signal": "Hold",
        "Nominal_Buy": 0,
        "Aggressive_Buy": 0.0,
        "Sentiment_Score": null
    },
    {
        "Ticker": "MCS",
        "Model": "DMA",
        "Strategy": "SMA",
        "Best_Window": 86,
        "Metric_Value": 0.9775454862014595,
        "Metric_Type": "roi",
        "Signal": "Hold",
        "Nominal_Buy": 0,
        "Aggressive_Buy": 0.0,
        "Sentiment_Score": null
    },
    {
        "Ticker": "MCD",
        "Model": "DMA",
        "Strategy": "SMA",
        "Best_Window": 10,
        "Metric_Value": 1.5364795261777178,
        "Metric_Type": "roi",
        "Signal": "Buy",
        "Nominal_Buy": 50,
        "Aggressive_Buy": 71.79005872684647,
        "Sentiment_Score": null
    },
    {
        "Ticker": "CSCO",
        "Model": "DMA",
        "Strategy": "SMA",
        "Best_Window": 99,
        "Metric_Value": 5.103771510387602,
        "Metric_Type": "roi",
        "Signal": "Hold",
        "Nominal_Buy": 0,
        "Aggressive_Buy": 0.0,
        "Sentiment_Score": null
    },
    {
        "Ticker": "PM",
        "Model": "DMA",
        "Strategy": "SMA",
        "Best_Window": 63,
        "Metric_Value": 2.1285572155907713,
        "Metric_Type": "roi",
        "Signal": "Hold",
        "Nominal_Buy": 0,
        "Aggressive_Buy": 0.0,
        "Sentiment_Score": null
    },
    {
        "Ticker": "TMUS",
        "Model": "DMA",
        "Strategy": "SMA",
        "Best_Window": 100,
        "Metric_Value": 5.966717241303428,
        "Metric_Type": "roi",
        "Signal": "Buy",
        "Nominal_Buy": 50,
        "Aggressive_Buy": 100.45663278536372,
        "Sentiment_Score": null
    },
    {
        "Ticker": "ABT",
        "Model": "DMA",
        "Strategy": "SMA",
        "Best_Window": 9,
        "Metric_Value": 1.107498617144396,
        "Metric_Type": "roi",
        "Signal": "Buy",
        "Nominal_Buy": 50,
        "Aggressive_Buy": 57.47023269889302,
        "Sentiment_Score": null
    },
    {
        "Ticker": "PFE",
        "Model": "DMA",
        "Strategy": "SMA",
        "Best_Window": 5,
        "Metric_Value": 0.3365076721218443,
        "Metric_Type": "roi",
        "Signal": "Buy",
        "Nominal_Buy": 50,
        "Aggressive_Buy": 61.363637919216465,
        "Sentiment_Score": null
    },
    {
        "Ticker": "GE",
        "Model": "DMA",
        "Strategy": "SMA",
        "Best_Window": 100,
        "Metric_Value": 5.51469343820183,
        "Metric_Type": "roi",
        "Signal": "Hold",
        "Nominal_Buy": 0,
        "Aggressive_Buy": 0.0,
        "Sentiment_Score": null
    },
    {
        "Ticker": "INTU",
        "Model": "DMA",
        "Strategy": "SMA",
        "Best_Window": 6,
        "Metric_Value": 1.3764436611670485,
        "Metric_Type": "roi",
        "Signal": "Buy",
        "Nominal_Buy": 50,
        "Aggressive_Buy": 78.03534010757214,
        "Sentiment_Score": null
    },
    {
        "Ticker": "IBM",
        "Model": "DMA",
        "Strategy": "SMA",
        "Best_Window": 100,
        "Metric_Value": 1.4375645788351212,
        "Metric_Type": "roi",
        "Signal": "Buy",
        "Nominal_Buy": 50,
        "Aggressive_Buy": 51.11678490987921,
        "Sentiment_Score": null
    },
    {
        "Ticker": "CAT",
        "Model": "DMA",
        "Strategy": "SMA",
        "Best_Window": 97,
        "Metric_Value": 10.699976293234538,
        "Metric_Type": "roi",
        "Signal": "Hold",
        "Nominal_Buy": 0,
        "Aggressive_Buy": 0.0,
        "Sentiment_Score": null
    },
    {
        "Ticker": "QCOM",
        "Model": "DMA",
        "Strategy": "SMA",
        "Best_Window": 18,
        "Metric_Value": 2.916967589190928,
        "Metric_Type": "roi",
        "Signal": "Buy",
        "Nominal_Buy": 50,
        "Aggressive_Buy": 53.938625849546185,
        "Sentiment_Score": null
    },
    {
        "Ticker": "VZ",
        "Model": "DMA",
        "Strategy": "SMA",
        "Best_Window": 8,
        "Metric_Value": 0.6426546371570931,
        "Metric_Type": "roi",
        "Signal": "Buy",
        "Nominal_Buy": 50,
        "Aggressive_Buy": 63.0759395962543,
        "Sentiment_Score": null
    },
    {
        "Ticker": "AMAT",
        "Model": "DMA",
        "Strategy": "SMA",
        "Best_Window": 84,
        "Metric_Value": 28.6271187550479,
        "Metric_Type": "roi",
        "Signal": "Hold",
        "Nominal_Buy": 0,
        "Aggressive_Buy": 0.0,
        "Sentiment_Score": null
    },
    {
        "Ticker": "TXN",
        "Model": "DMA",
        "Strategy": "SMA",
        "Best_Window": 88,
        "Metric_Value": 6.154017171515371,
        "Metric_Type": "roi",
        "Signal": "Hold",
        "Nominal_Buy": 0,
        "Aggressive_Buy": 0.0,
        "Sentiment_Score": null
    },
    {
        "Ticker": "NOW",
        "Model": "DMA",
        "Strategy": "SMA",
        "Best_Window": 7,
        "Metric_Value": 2.9358753424069333,
        "Metric_Type": "roi",
        "Signal": "Buy",
        "Nominal_Buy": 50,
        "Aggressive_Buy": 83.15311500869922,
        "Sentiment_Score": null
    },
    {
        "Ticker": "ISRG",
        "Model": "DMA",
        "Strategy": "SMA",
        "Best_Window": 100,
        "Metric_Value": 4.056681479136181,
        "Metric_Type": "roi",
        "Signal": "Buy",
        "Nominal_Buy": 50,
        "Aggressive_Buy": 122.49458416194166,
        "Sentiment_Score": null
    },
    {
        "Ticker": "MS",
        "Model": "DMA",
        "Strategy": "SMA",
        "Best_Window": 100,
        "Metric_Value": 9.361192592153499,
        "Metric_Type": "roi",
        "Signal": "Hold",
        "Nominal_Buy": 0,
        "Aggressive_Buy": 0.0,
        "Sentiment_Score": null
    },
    {
        "Ticker": "DHR",
        "Model": "DMA",
        "Strategy": "SMA",
        "Best_Window": 8,
        "Metric_Value": 2.65164801103639,
        "Metric_Type": "roi",
        "Signal": "Buy",
        "Nominal_Buy": 50,
        "Aggressive_Buy": 55.110412995189215,
        "Sentiment_Score": null
    },
    {
        "Ticker": "HON",
        "Model": "DMA",
        "Strategy": "SMA",
        "Best_Window": 5,
        "Metric_Value": 1.9493081550540303,
        "Metric_Type": "roi",
        "Signal": "Buy",
        "Nominal_Buy": 50,
        "Aggressive_Buy": 50.91184157883883,
        "Sentiment_Score": null
    },
    {
        "Ticker": "RTX",
        "Model": "DMA",
        "Strategy": "SMA",
        "Best_Window": 99,
        "Metric_Value": 2.455964538005638,
        "Metric_Type": "roi",
        "Signal": "Buy",
        "Nominal_Buy": 50,
        "Aggressive_Buy": 72.34789968017704,
        "Sentiment_Score": null
    },
    {
        "Ticker": "AMGN",
        "Model": "DMA",
        "Strategy": "SMA",
        "Best_Window": 6,
        "Metric_Value": 2.4311618175785923,
        "Metric_Type": "roi",
        "Signal": "Buy",
        "Nominal_Buy": 50,
        "Aggressive_Buy": 52.23128214049162,
        "Sentiment_Score": null
    },
    {
        "Ticker": "BKNG",
        "Model": "DMA",
        "Strategy": "SMA",
        "Best_Window": 72,
        "Metric_Value": 3.2334479082953105,
        "Metric_Type": "roi",
        "Signal": "Buy",
        "Nominal_Buy": 50,
        "Aggressive_Buy": 55.72455068489619,
        "Sentiment_Score": null
    },
    {
        "Ticker": "UNP",
        "Model": "DMA",
        "Strategy": "SMA",
        "Best_Window": 5,
        "Metric_Value": 2.213164160592554,
        "Metric_Type": "roi",
        "Signal": "Buy",
        "Nominal_Buy": 50,
        "Aggressive_Buy": 53.87056958826104,
        "Sentiment_Score": null
    },
    {
        "Ticker": "LOW",
        "Model": "DMA",
        "Strategy": "SMA",
        "Best_Window": 100,
        "Metric_Value": 3.5356334817830626,
        "Metric_Type": "roi",
        "Signal": "Buy",
        "Nominal_Buy": 50,
        "Aggressive_Buy": 111.26400104249419,
        "Sentiment_Score": null
    },
    {
        "Ticker": "SPGI",
        "Model": "DMA",
        "Strategy": "SMA",
        "Best_Window": 6,
        "Metric_Value": 3.6950119629610714,
        "Metric_Type": "roi",
        "Signal": "Buy",
        "Nominal_Buy": 50,
        "Aggressive_Buy": 63.95467441775222,
        "Sentiment_Score": null
    },
    {
        "Ticker": "SYK",
        "Model": "DMA",
        "Strategy": "SMA",
        "Best_Window": 98,
        "Metric_Value": 2.2917990394435215,
        "Metric_Type": "roi",
        "Signal": "Buy",
        "Nominal_Buy": 50,
        "Aggressive_Buy": 96.76020738791597,
        "Sentiment_Score": null
    },
    {
        "Ticker": "GS",
        "Model": "DMA",
        "Strategy": "SMA",
        "Best_Window": 100,
        "Metric_Value": 7.018731541061739,
        "Metric_Type": "roi",
        "Signal": "Hold",
        "Nominal_Buy": 0,
        "Aggressive_Buy": 0.0,
        "Sentiment_Score": null
    },
    {
        "Ticker": "SCHW",
        "Model": "DMA",
        "Strategy": "SMA",
        "Best_Window": 100,
        "Metric_Value": 2.900937040010271,
        "Metric_Type": "roi",
        "Signal": "Buy",
        "Nominal_Buy": 50,
        "Aggressive_Buy": 56.44297982948216,
        "Sentiment_Score": null
    },
    {
        "Ticker": "TJX",
        "Model": "DMA",
        "Strategy": "SMA",
        "Best_Window": 5,
        "Metric_Value": 4.723889468974635,
        "Metric_Type": "roi",
        "Signal": "Buy",
        "Nominal_Buy": 50,
        "Aggressive_Buy": 52.99081377575794,
        "Sentiment_Score": null
    },
    {
        "Ticker": "NEE",
        "Model": "DMA",
        "Strategy": "SMA",
        "Best_Window": 6,
        "Metric_Value": 2.81043272210989,
        "Metric_Type": "roi",
        "Signal": "Buy",
        "Nominal_Buy": 50,
        "Aggressive_Buy": 50.40659673173338,
        "Sentiment_Score": null
    },
    {
        "Ticker": "COP",
        "Model": "DMA",
        "Strategy": "SMA",
        "Best_Window": 94,
        "Metric_Value": 1.7517380419188175,
        "Metric_Type": "roi",
        "Signal": "Buy",
        "Nominal_Buy": 50,
        "Aggressive_Buy": 89.18891421938497,
        "Sentiment_Score": null
    },
    {
        "Ticker": "PGR",
        "Model": "DMA",
        "Strategy": "SMA",
        "Best_Window": 11,
        "Metric_Value": 6.277906094312503,
        "Metric_Type": "roi",
        "Signal": "Hold",
        "Nominal_Buy": 0,
        "Aggressive_Buy": 0.0,
        "Sentiment_Score": null
    },
    {
        "Ticker": "ELV",
        "Model": "DMA",
        "Strategy": "SMA",
        "Best_Window": 65,
        "Metric_Value": 2.3911547129136563,
        "Metric_Type": "roi",
        "Signal": "Hold",
        "Nominal_Buy": 0,
        "Aggressive_Buy": 0.0,
        "Sentiment_Score": null
    },
    {
        "Ticker": "ETN",
        "Model": "DMA",
        "Strategy": "SMA",
        "Best_Window": 97,
        "Metric_Value": 7.046631229811107,
        "Metric_Type": "roi",
        "Signal": "Hold",
        "Nominal_Buy": 0,
        "Aggressive_Buy": 0.0,
        "Sentiment_Score": null
    },
    {
        "Ticker": "BSX",
        "Model": "DMA",
        "Strategy": "SMA",
        "Best_Window": 82,
        "Metric_Value": 2.192311996933706,
        "Metric_Type": "roi",
        "Signal": "Buy",
        "Nominal_Buy": 50,
        "Aggressive_Buy": 229.92409933769892,
        "Sentiment_Score": null
    },
    {
        "Ticker": "REGN",
        "Model": "DMA",
        "Strategy": "SMA",
        "Best_Window": 8,
        "Metric_Value": 2.7684693222145067,
        "Metric_Type": "roi",
        "Signal": "Hold",
        "Nominal_Buy": 0,
        "Aggressive_Buy": 0.0,
        "Sentiment_Score": null
    },
    {
        "Ticker": "LMT",
        "Model": "DMA",
        "Strategy": "SMA",
        "Best_Window": 9,
        "Metric_Value": 2.6475298856544813,
        "Metric_Type": "roi",
        "Signal": "Buy",
        "Nominal_Buy": 50,
        "Aggressive_Buy": 84.32153775782577,
        "Sentiment_Score": null
    },
    {
        "Ticker": "VRTX",
        "Model": "DMA",
        "Strategy": "SMA",
        "Best_Window": 99,
        "Metric_Value": 4.841010836863753,
        "Metric_Type": "roi",
        "Signal": "Hold",
        "Nominal_Buy": 0,
        "Aggressive_Buy": 0.0,
        "Sentiment_Score": null
    },
    {
        "Ticker": "CB",
        "Model": "DMA",
        "Strategy": "SMA",
        "Best_Window": 11,
        "Metric_Value": 2.3446472420084934,
        "Metric_Type": "roi",
        "Signal": "Buy",
        "Nominal_Buy": 50,
        "Aggressive_Buy": 51.405338173603774,
        "Sentiment_Score": null
    },
    {
        "Ticker": "PANW",
        "Model": "DMA",
        "Strategy": "SMA",
        "Best_Window": 100,
        "Metric_Value": 11.373549668790545,
        "Metric_Type": "roi",
        "Signal": "Hold",
        "Nominal_Buy": 0,
        "Aggressive_Buy": 0.0,
        "Sentiment_Score": null
    },
    {
        "Ticker": "MU",
        "Model": "DMA",
        "Strategy": "SMA",
        "Best_Window": 100,
        "Metric_Value": 84.3180723547623,
        "Metric_Type": "roi",
        "Signal": "Hold",
        "Nominal_Buy": 0,
        "Aggressive_Buy": 0.0,
        "Sentiment_Score": null
    },
    {
        "Ticker": "ADP",
        "Model": "DMA",
        "Strategy": "SMA",
        "Best_Window": 9,
        "Metric_Value": 1.954121595277547,
        "Metric_Type": "roi",
        "Signal": "Buy",
        "Nominal_Buy": 50,
        "Aggressive_Buy": 69.32773177625113,
        "Sentiment_Score": null
    },
    {
        "Ticker": "CI",
        "Model": "DMA",
        "Strategy": "SMA",
        "Best_Window": 5,
        "Metric_Value": 1.9180213840759044,
        "Metric_Type": "roi",
        "Signal": "Buy",
        "Nominal_Buy": 50,
        "Aggressive_Buy": 57.71058974508498,
        "Sentiment_Score": null
    },
    {
        "Ticker": "MDLZ",
        "Model": "DMA",
        "Strategy": "SMA",
        "Best_Window": 8,
        "Metric_Value": 0.8697582957338206,
        "Metric_Type": "roi",
        "Signal": "Buy",
        "Nominal_Buy": 50,
        "Aggressive_Buy": 69.52404631123383,
        "Sentiment_Score": null
    },
    {
        "Ticker": "PLD",
        "Model": "DMA",
        "Strategy": "SMA",
        "Best_Window": 98,
        "Metric_Value": 2.879242412043441,
        "Metric_Type": "roi",
        "Signal": "Hold",
        "Nominal_Buy": 0,
        "Aggressive_Buy": 0.0,
        "Sentiment_Score": null
    },
    {
        "Ticker": "SBUX",
        "Model": "DMA",
        "Strategy": "SMA",
        "Best_Window": 6,
        "Metric_Value": 1.863131831905683,
        "Metric_Type": "roi",
        "Signal": "Buy",
        "Nominal_Buy": 50,
        "Aggressive_Buy": 55.01746634883493,
        "Sentiment_Score": null
    },
    {
        "Ticker": "DE",
        "Model": "DMA",
        "Strategy": "SMA",
        "Best_Window": 97,
        "Metric_Value": 4.7956107955993765,
        "Metric_Type": "roi",
        "Signal": "Hold",
        "Nominal_Buy": 0,
        "Aggressive_Buy": 0.0,
        "Sentiment_Score": null
    },
    {
        "Ticker": "ADI",
        "Model": "DMA",
        "Strategy": "SMA",
        "Best_Window": 8,
        "Metric_Value": 7.0225882950127,
        "Metric_Type": "roi",
        "Signal": "Hold",
        "Nominal_Buy": 0,
        "Aggressive_Buy": 0.0,
        "Sentiment_Score": null
    },
    {
        "Ticker": "AMT",
        "Model": "DMA",
        "Strategy": "SMA",
        "Best_Window": 6,
        "Metric_Value": 1.0462022194648248,
        "Metric_Type": "roi",
        "Signal": "Buy",
        "Nominal_Buy": 50,
        "Aggressive_Buy": 65.30353197637379,
        "Sentiment_Score": null
    },
    {
        "Ticker": "GILD",
        "Model": "DMA",
        "Strategy": "SMA",
        "Best_Window": 52,
        "Metric_Value": 2.3906196718195933,
        "Metric_Type": "roi",
        "Signal": "Buy",
        "Nominal_Buy": 50,
        "Aggressive_Buy": 74.75912331979224,
        "Sentiment_Score": null
    },
    {
        "Ticker": "KLAC",
        "Model": "DMA",
        "Strategy": "SMA",
        "Best_Window": 100,
        "Metric_Value": 47.245654473521654,
        "Metric_Type": "roi",
        "Signal": "Hold",
        "Nominal_Buy": 0,
        "Aggressive_Buy": 0.0,
        "Sentiment_Score": null
    },
    {
        "Ticker": "BA",
        "Model": "DMA",
        "Strategy": "SMA",
        "Best_Window": 10,
        "Metric_Value": 0.802598160092362,
        "Metric_Type": "roi",
        "Signal": "Hold",
        "Nominal_Buy": 0,
        "Aggressive_Buy": 0.0,
        "Sentiment_Score": null
    },
    {
        "Ticker": "LRCX",
        "Model": "DMA",
        "Strategy": "SMA",
        "Best_Window": 46,
        "Metric_Value": 49.759392742173105,
        "Metric_Type": "roi",
        "Signal": "Hold",
        "Nominal_Buy": 0,
        "Aggressive_Buy": 0.0,
        "Sentiment_Score": null
    },
    {
        "Ticker": "MO",
        "Model": "DMA",
        "Strategy": "SMA",
        "Best_Window": 5,
        "Metric_Value": 2.0731991795955254,
        "Metric_Type": "roi",
        "Signal": "Hold",
        "Nominal_Buy": 0,
        "Aggressive_Buy": 0.0,
        "Sentiment_Score": null
    },
    {
        "Ticker": "CRWD",
        "Model": "DMA",
        "Strategy": "SMA",
        "Best_Window": 74,
        "Metric_Value": 4.621474002994451,
        "Metric_Type": "roi",
        "Signal": "Hold",
        "Nominal_Buy": 0,
        "Aggressive_Buy": 0.0,
        "Sentiment_Score": null
    },
    {
        "Ticker": "T",
        "Model": "DMA",
        "Strategy": "SMA",
        "Best_Window": 8,
        "Metric_Value": 0.74830749687922,
        "Metric_Type": "roi",
        "Signal": "Buy",
        "Nominal_Buy": 50,
        "Aggressive_Buy": 66.94003891508977,
        "Sentiment_Score": null
    },
    {
        "Ticker": "CMG",
        "Model": "DMA",
        "Strategy": "SMA",
        "Best_Window": 5,
        "Metric_Value": 1.9019778643240512,
        "Metric_Type": "roi",
        "Signal": "Buy",
        "Nominal_Buy": 50,
        "Aggressive_Buy": 74.65618386890233,
        "Sentiment_Score": null
    },
    {
        "Ticker": "ICE",
        "Model": "DMA",
        "Strategy": "SMA",
        "Best_Window": 100,
        "Metric_Value": 2.010990098675928,
        "Metric_Type": "roi",
        "Signal": "Buy",
        "Nominal_Buy": 50,
        "Aggressive_Buy": 142.021326638705,
        "Sentiment_Score": null
    }
]